WorldWeatherPy/__init__.py
WorldWeatherPy/attribute_list.py
WorldWeatherPy/by_attribute.py
WorldWeatherPy/historical_weather.py
WorldWeatherPy-0.0.3.dist-info/LICENSE
WorldWeatherPy-0.0.3.dist-info/METADATA
WorldWeatherPy-0.0.3.dist-info/WHEEL
WorldWeatherPy-0.0.3.dist-info/top_level.txt
WorldWeatherPy-0.0.3.dist-info/RECORD
