Metadata-Version: 2.1
Name: WorldWeatherPy
Version: 0.0.3
Summary: A Python library which acts as a wrapper for the WorldWeatherOnline API.
Home-page: https://github.com/David-Woroniuk/Weather-API
Author: David Woroniuk
Author-email: david.j.woroniuk@durham.ac.uk
License: MIT License
Platform: UNKNOWN
Requires-Dist: pandas
Requires-Dist: requests
